DESCRIPTION.rst
MANIFEST.in
README.rst
setup.cfg
setup.py
pyem7/__init__.py
pyem7/account.py
pyem7/asset.py
pyem7/base_api.py
pyem7/custom_errors.py
pyem7/device.py
pyem7/discovery.py
pyem7/organization.py
pyem7.egg-info/PKG-INFO
pyem7.egg-info/SOURCES.txt
pyem7.egg-info/dependency_links.txt
pyem7.egg-info/pbr.json
pyem7.egg-info/requires.txt
pyem7.egg-info/top_level.txt