Metadata-Version: 1.1
Name: pyem7
Version: 0.0.dev1
Summary: Library for accessing the Science Logic EM7
Home-page: https://github.com/the-kid89/pyem7
Author: Emett Speer
Author-email: pyem7@emettspeer.com
License: BSD-3
Keywords: library,rest,sciencelogic,em7
Platform: UNKNOWN
Classifier: Development Status :: 3 - Alpha
Classifier: Intended Audience :: Developers
Classifier: Topic :: Software Development :: Libraries :: Python Modules
Classifier: License :: OSI Approved :: BSD License
Classifier: Programming Language :: Python
Classifier: Programming Language :: Python :: 3.2
Classifier: Programming Language :: Python :: 3.3
Classifier: Programming Language :: Python :: 3.4
